MANIFEST.in
README.md
setup.py
richtextpy/__init__.py
richtextpy/delta.py
richtextpy/op.py
richtextpy/opiterator.py
richtextpy/type.py
richtextpy/type_utils.py
richtextpy.egg-info/PKG-INFO
richtextpy.egg-info/SOURCES.txt
richtextpy.egg-info/dependency_links.txt
richtextpy.egg-info/not-zip-safe
richtextpy.egg-info/requires.txt
richtextpy.egg-info/top_level.txt