Metadata-Version: 1.1
Name: richtextpy
Version: 0.2
Summary: An operational transformation library for rich text documents
Home-page: http://github.com/sachinrekhi/richtextpy
Author: Sachin Rekhi
Author-email: sachin.rekhi@gmail.com
License: MIT
Keywords: operational transformation type rich text
Platform: UNKNOWN
Classifier: Programming Language :: Python :: 2.7
Classifier: License :: OSI Approved :: MIT License
